niwrap_afni/afni/__init__.py
niwrap_afni/afni/abids_json_info_py.py
niwrap_afni/afni/abids_json_tool_py.py
niwrap_afni/afni/abids_tool_py.py
niwrap_afni/afni/adjunct_apqc_tsnr_general.py
niwrap_afni/afni/adjunct_aw_tableize_roi_info_py.py
niwrap_afni/afni/adjunct_calc_mont_dims_py.py
niwrap_afni/afni/adjunct_combine_str_py.py
niwrap_afni/afni/adjunct_is_label_py.py
niwrap_afni/afni/adjunct_make_script_and_rst_py.py
niwrap_afni/afni/adjunct_select_str_py.py
niwrap_afni/afni/adjunct_simplify_cost_py.py
niwrap_afni/afni/adjunct_suma_fs_mask_and_qc.py
niwrap_afni/afni/adjunct_suma_fs_roi_info.py
niwrap_afni/afni/adjunct_tort_plot_dp_align.py
niwrap_afni/afni/adwarp.py
niwrap_afni/afni/afni.py
niwrap_afni/afni/afni_batch_r.py
niwrap_afni/afni/afni_check_omp.py
niwrap_afni/afni/afni_history.py
niwrap_afni/afni/afni_open.py
niwrap_afni/afni/afni_proc_py.py
niwrap_afni/afni/afni_run_r.py
niwrap_afni/afni/afni_system_check_py.py
niwrap_afni/afni/aiv.py
niwrap_afni/afni/align_epi_anat_py.py
niwrap_afni/afni/analyze_trace.py
niwrap_afni/afni/ap_run_simple_rest_tcsh.py
niwrap_afni/afni/apqc_make_html_py.py
niwrap_afni/afni/apqc_make_tcsh_py.py
niwrap_afni/afni/apsearch.py
niwrap_afni/afni/auto_warp_py.py
niwrap_afni/afni/balloon.py
niwrap_afni/afni/bayes_view.py
niwrap_afni/afni/bayesian_group_ana_py.py
niwrap_afni/afni/brain_skin.py
niwrap_afni/afni/build_afni_py.py
niwrap_afni/afni/cat_matvec.py
niwrap_afni/afni/ccalc.py
niwrap_afni/afni/cifti_tool.py
niwrap_afni/afni/cjpeg.py
niwrap_afni/afni/clust_exp_hist_table_py.py
niwrap_afni/afni/clust_exp_stat_parse_py.py
niwrap_afni/afni/column_cat.py
niwrap_afni/afni/compare_surfaces.py
niwrap_afni/afni/convert_cdiflist_to_grads_py.py
niwrap_afni/afni/convert_dset.py
niwrap_afni/afni/convert_surface.py
niwrap_afni/afni/convex_hull.py
niwrap_afni/afni/count.py
niwrap_afni/afni/create_icosahedron.py
niwrap_afni/afni/dcm2niix_afni.py
niwrap_afni/afni/dicom_hdr.py
niwrap_afni/afni/dicom_hinfo.py
niwrap_afni/afni/dicom_to_raw.py
niwrap_afni-0.8.3.dist-info/WHEEL
niwrap_afni-0.8.3.dist-info/METADATA
niwrap_afni-0.8.3.dist-info/RECORD
